{
  "gitSyncId": "6875e74837a75f65b1cc20a8_69788858-e1f9-4401-8089-ae2d4fb30baf",
  "id": "MainPage_mainFunctions.modificaRiga",
  "pluginId": "js-plugin",
  "pluginType": "JS",
  "unpublishedAction": {
    "actionConfiguration": {
      "encodeParamsToggle": true,
      "jsArguments": [],
      "paginationType": "NONE",
      "timeoutInMillisecond": 10000
    },
    "collectionId": "MainPage_mainFunctions",
    "confirmBeforeExecute": false,
    "datasource": {
      "isAutoGenerated": false,
      "name": "UNUSED_DATASOURCE",
      "pluginId": "js-plugin"
    },
    "dynamicBindingPathList": [
      {
        "key": "body"
      }
    ],
    "fullyQualifiedName": "mainFunctions.modificaRiga",
    "name": "modificaRiga",
    "pageId": "MainPage",
    "runBehaviour": "MANUAL",
    "userSetOnLoad": false
  }
}